passtools/__init__.py
pypasstools-0.0.11.dist-info/LICENCE
pypasstools-0.0.11.dist-info/METADATA
pypasstools-0.0.11.dist-info/WHEEL
pypasstools-0.0.11.dist-info/top_level.txt
pypasstools-0.0.11.dist-info/RECORD
