Metadata-Version: 2.1
Name: pypasstools
Version: 0.0.11
Summary: Passtools is a package that allows you to use tools with which you can do all kinds of stuff with passwords
Home-page: https://github.com/Ayaan-Imran/passtools
Author: Ayaan Imran Saleem
Author-email: miskiacuberayaan2509@gmail.com
License: UNKNOWN
Platform: UNKNOWN
Classifier: Programming Language :: Python :: 3
Classifier: License :: OSI Approved :: MIT License
Classifier: Operating System :: OS Independent
License-File: LICENCE
